alexsandbox/__init__.py
gp_framework/__init__.py
gp_framework/bytegenotype.py
gp_framework/config.py
gp_framework/evolutionary_optimizer.py
gp_framework/exception.py
gp_framework/fitness_calculator.py
gp_framework/floatgenotype.py
gp_framework/genotype.py
gp_framework/meiosis.py
gp_framework/mitosis.py
gp_framework/population_manager.py
gp_framework/report.py
gp_framework/serializer.py
gp_framework/phenotype/__init__.py
gp_framework/phenotype/blackjack.py
gp_framework/phenotype/number_generator.py
gp_framework/phenotype/phenotype.py
gp_framework/phenotype/string_search.py
gp_framework/phenotype/test/__init__.py
gp_framework/phenotype/test/blackjack.py
gp_framework/test/__init__.py
gp_framework/test/test_gp_framework.py
gp_framework/test/test_report.py
sim/__init__.py
sim/main.py
sim/meiosis.py
sim/mitosis.py
sim/test/__init__.py
GP_Framework_BYU_HCMI-0.0.10.dist-info/LICENSE
GP_Framework_BYU_HCMI-0.0.10.dist-info/METADATA
GP_Framework_BYU_HCMI-0.0.10.dist-info/WHEEL
GP_Framework_BYU_HCMI-0.0.10.dist-info/top_level.txt
GP_Framework_BYU_HCMI-0.0.10.dist-info/RECORD
