Metadata-Version: 2.1
Name: GP-Framework-BYU-HCMI
Version: 0.0.10
Summary: Contains some basic genetic algorithms that can be used for arbitrary applications
Home-page: https://github.com/CalixBarrus/GP-Demo
Author: A. Anthon/C. Barrus
Author-email: 
License: UNKNOWN
Platform: UNKNOWN
Classifier: Programming Language :: Python :: 3
Classifier: License :: OSI Approved :: MIT License
Classifier: Operating System :: OS Independent
Requires-Python: >=3.6
